{
    "target_identifiers": {
        "pmid": "23338275",
        "doi": "10.1590/s0103-64402012000600024",
        "url": "https://www.scielo.br/j/bdj/a/9jGWNV3YgTQNXphZz67BgkC/?lang=en&format=pdf"
    },
    "network_context": {
        "request_headers": {
            "User-Agent": "Mozilla/5.0 (Windows NT 10.0; Win64; x64) AppleWebKit/537.36 (KHTML, like Gecko) Chrome/122.0.0.0 Safari/537.36 Edg/122.0.0.0",
            "Accept-Encoding": "gzip, deflate, zstd",
            "Accept": "text/html,application/xhtml+xml,application/xml;q=0.9,image/avif,image/webp,image/apng,*/*;q=0.8",
            "Connection": "keep-alive",
            "Accept-Language": "en-US,en;q=0.9",
            "Sec-Ch-Ua": "\"Not A(Brand\";v=\"99\", \"Google Chrome\";v=\"121\", \"Chromium\";v=\"121\"",
            "Sec-Ch-Ua-Mobile": "?0",
            "Sec-Ch-Ua-Platform": "\"Windows\"",
            "Upgrade-Insecure-Requests": "1",
            "Email": "chemahc94@pusan.ac.kr"
        },
        "user_agent": "Mozilla/5.0 (Windows NT 10.0; Win64; x64) AppleWebKit/537.36 (KHTML, like Gecko) Chrome/122.0.0.0 Safari/537.36 Edg/122.0.0.0",
        "proxy_vpn_used": "None"
    },
    "http_status": {
        "status_code": 200,
        "body_snippet": "Could not decode body"
    },
    "anti_bot_sign": {
        "detected_signs": [],
        "has_anti_bot": false
    },
    "exception": "('Connection broken: IncompleteRead(3334528 bytes read, 799218 more expected)', IncompleteRead(3334528 bytes read, 799218 more expected))"
}